odoo/addons/stock_request_mrp/README.rst
odoo/addons/stock_request_mrp/__init__.py
odoo/addons/stock_request_mrp/__manifest__.py
odoo/addons/stock_request_mrp/hooks.py
odoo/addons/stock_request_mrp/i18n/es.po
odoo/addons/stock_request_mrp/i18n/it.po
odoo/addons/stock_request_mrp/i18n/stock_request_mrp.pot
odoo/addons/stock_request_mrp/models/__init__.py
odoo/addons/stock_request_mrp/models/mrp_production.py
odoo/addons/stock_request_mrp/models/stock_request.py
odoo/addons/stock_request_mrp/models/stock_request_order.py
odoo/addons/stock_request_mrp/models/stock_rule.py
odoo/addons/stock_request_mrp/readme/CONTRIBUTORS.rst
odoo/addons/stock_request_mrp/readme/DESCRIPTION.rst
odoo/addons/stock_request_mrp/readme/ROADMAP.rst
odoo/addons/stock_request_mrp/readme/USAGE.rst
odoo/addons/stock_request_mrp/security/ir.model.access.csv
odoo/addons/stock_request_mrp/static/description/icon.png
odoo/addons/stock_request_mrp/static/description/index.html
odoo/addons/stock_request_mrp/tests/__init__.py
odoo/addons/stock_request_mrp/tests/test_stock_request_mrp.py
odoo/addons/stock_request_mrp/views/mrp_production_views.xml
odoo/addons/stock_request_mrp/views/stock_request_order_views.xml
odoo/addons/stock_request_mrp/views/stock_request_views.xml
odoo14_addon_stock_request_mrp-14.0.1.2.0.dist-info/METADATA
odoo14_addon_stock_request_mrp-14.0.1.2.0.dist-info/WHEEL
odoo14_addon_stock_request_mrp-14.0.1.2.0.dist-info/top_level.txt
odoo14_addon_stock_request_mrp-14.0.1.2.0.dist-info/RECORD
